aplay/__init__.py
aplay/kernel/__init__.py
aplay/kernel/actor.py
aplay/kernel/const.py
aplay/kernel/logger.py
aplay/kernel/system.py
aplay/mailbox/__init__.py
aplay/mailbox/base.py
aplay/mailbox/msg_serializer.py
aplay/mailbox/queue_mailbox.py
aplay/mailbox/redis_box.py
aplay/mailstation/__init__.py
aplay/mailstation/base.py
aplay/mailstation/compose.py
aplay/mailstation/hash_redis.py
aplay/mailstation/simple.py
async_actor/__init__.py
async_actor/kernel/__init__.py
async_actor/kernel/actor.py
async_actor/kernel/const.py
async_actor/kernel/logger.py
async_actor/kernel/system.py
async_play/__init__.py
async_play/kernel/__init__.py
async_play/kernel/actor.py
async_play/kernel/const.py
async_play/kernel/logger.py
async_play/kernel/system.py
aplay-1.1.1.dist-info/LICENSE
aplay-1.1.1.dist-info/METADATA
aplay-1.1.1.dist-info/WHEEL
aplay-1.1.1.dist-info/top_level.txt
aplay-1.1.1.dist-info/RECORD
