Metadata-Version: 2.1
Name: aplay
Version: 1.1.1
Summary: asyncio actor model implemention for easy use
Home-page: https://github.com/aohan237/aplay
Author: aohan237
Author-email: aohan237@gmail.com
License: GNU AGPLv3
Platform: POSIX
Classifier: License :: OSI Approved :: MIT License
Classifier: Programming Language :: Python
Classifier: Programming Language :: Python :: 3.5
Classifier: Programming Language :: Python :: 3.6
Classifier: Programming Language :: Python :: 3.7
Classifier: Programming Language :: Python :: 3.8
Classifier: Programming Language :: Python :: 3.9
Classifier: Operating System :: POSIX
Classifier: Environment :: Web Environment
Classifier: Intended Audience :: Developers
Classifier: Topic :: Software Development
Classifier: Topic :: Software Development :: Libraries
License-File: LICENSE
Requires-Dist: aioredis
Requires-Dist: psutil
Requires-Dist: msgpack
